navstack_gym/__init__.py
navstack_gym/base.py
navstack_gym/maintask_env.py
navstack_gym/subtasks_env.py
navstack_gym/utils.py
navstack_gym-0.1.16.dist-info/WHEEL
navstack_gym-0.1.16.dist-info/METADATA
navstack_gym-0.1.16.dist-info/RECORD
