Metadata-Version: 2.1
Name: navstack-gym
Version: 0.1.16
Summary: Simulation environment of task with autonomous mobile robot using Navigation Stack
Home-page: https://github.com/wwwshwww/navstack-gym
Author: Reona Sato
Author-email: www.shinderu.www@gmail.com
Requires-Python: >=3.7,<3.10
Classifier: Programming Language :: Python :: 3
Classifier: Programming Language :: Python :: 3.7
Classifier: Programming Language :: Python :: 3.8
Classifier: Programming Language :: Python :: 3.9
Requires-Dist: descartes (>=1.1.0,<2.0.0)
Requires-Dist: gym (>=0.19.0)
Requires-Dist: matplotlib (>=3.5.0,<4.0.0)
Requires-Dist: nav-sim-modules (>=0.3.8)
